lurara/__init__.py
lurara/_basic.py
lurara/act.py
lurara/main.py
lurara/augment/__init__.py
lurara/augment/img_augment.py
lurara/data/__init__.py
lurara/data/datacontrol.py
lurara/data/stdata.py
lurara/ops/__init__.py
lurara/ops/conv.py
lurara/ops/lstm.py
lurara/ops/pooling.py
lurara/ops/reshape.py
lurara/ops/sample.py
lurara/prefab/__init__.py
lurara/prefab/yolo.py
lurara/prehandle/__init__.py
lurara/prehandle/resize.py
lutils/__init__.py
lutils/_basic.py
lutils/act.py
lutils/main.py
lutils/augment/__init__.py
lutils/augment/img_augment.py
lutils/data/__init__.py
lutils/data/datacontrol.py
lutils/data/stdata.py
lutils/ops/__init__.py
lutils/ops/conv.py
lutils/ops/pooling.py
lutils/ops/sample.py
lutils/prefab/__init__.py
lutils/prefab/yolo.py
lutils/prehandle/__init__.py
lutils/prehandle/resize.py
lurara-0.1.5.dist-info/METADATA
lurara-0.1.5.dist-info/WHEEL
lurara-0.1.5.dist-info/top_level.txt
lurara-0.1.5.dist-info/RECORD
