Metadata-Version: 2.1
Name: lurara
Version: 0.1.5
Summary: more easy use for keras(care for it used in small or mid model, not efficiency). simplify like dataset create, model train&predict. Used by person
Author-email: 2229066748@qq.com
Maintainer: Eagle'sBaby
Maintainer-email: 2229066748@qq.com
License: Apache Licence 2.0
Keywords: keras,utils
Classifier: Programming Language :: Python
Classifier: Programming Language :: Python :: 3
Requires-Python: >=3
Requires-Dist: keras ==2.6.0
Requires-Dist: files3
